[
  {
    "iter": 1,
    "ep_wins": 9,
    "ep_losses": 23,
    "ep_draws": 0,
    "recent_winrate": 0.28125,
    "policy_loss": -0.007004294133399265,
    "value_loss": 0.5150027370529461,
    "entropy": 0.4106033880615977,
    "elapsed_s": 12.349560468981508
  },
  {
    "iter": 2,
    "ep_wins": 9,
    "ep_losses": 23,
    "ep_draws": 0,
    "recent_winrate": 0.28125,
    "policy_loss": -0.01188952847345111,
    "value_loss": 0.39169651881598194,
    "entropy": 0.4059927915876313,
    "elapsed_s": 26.0912553909875
  },
  {
    "iter": 3,
    "ep_wins": 9,
    "ep_losses": 23,
    "ep_draws": 0,
    "recent_winrate": 0.28125,
    "policy_loss": -0.0038042019363134527,
    "value_loss": 0.46730742980616397,
    "entropy": 0.39436516936564164,
    "elapsed_s": 36.02651668197359
  },
  {
    "iter": 4,
    "ep_wins": 8,
    "ep_losses": 24,
    "ep_draws": 0,
    "recent_winrate": 0.25,
    "policy_loss": 0.0008294897103414997,
    "value_loss": 0.26041209729621434,
    "entropy": 0.3896716998044447,
    "elapsed_s": 49.03173780697398
  },
  {
    "iter": 5,
    "ep_wins": 6,
    "ep_losses": 26,
    "ep_draws": 0,
    "recent_winrate": 0.1875,
    "policy_loss": 0.010326368247110383,
    "value_loss": 0.21779406975552162,
    "entropy": 0.4125135726606316,
    "elapsed_s": 63.343184477998875
  },
  {
    "iter": 6,
    "ep_wins": 17,
    "ep_losses": 15,
    "ep_draws": 0,
    "recent_winrate": 0.53125,
    "policy_loss": -0.011682922851559849,
    "value_loss": 0.46319653061052213,
    "entropy": 0.358397699266291,
    "elapsed_s": 74.07964609799092
  },
  {
    "iter": 7,
    "ep_wins": 6,
    "ep_losses": 26,
    "ep_draws": 0,
    "recent_winrate": 0.1875,
    "policy_loss": -0.007209936443769038,
    "value_loss": 0.18225807689269063,
    "entropy": 0.3953057619131843,
    "elapsed_s": 90.1841012009827
  },
  {
    "iter": 8,
    "ep_wins": 13,
    "ep_losses": 19,
    "ep_draws": 0,
    "recent_winrate": 0.40625,
    "policy_loss": -0.008508197951250622,
    "value_loss": 0.32102727357922445,
    "entropy": 0.4055196065747425,
    "elapsed_s": 104.54108874598751
  },
  {
    "iter": 9,
    "ep_wins": 4,
    "ep_losses": 28,
    "ep_draws": 0,
    "recent_winrate": 0.125,
    "policy_loss": -0.007137380531639792,
    "value_loss": 0.19718897053495316,
    "entropy": 0.39376651262397055,
    "elapsed_s": 119.96495203097584
  },
  {
    "iter": 10,
    "ep_wins": 6,
    "ep_losses": 26,
    "ep_draws": 0,
    "recent_winrate": 0.1875,
    "policy_loss": -0.005623062066112495,
    "value_loss": 0.21490547940729823,
    "entropy": 0.4163978406839191,
    "elapsed_s": 133.09343807399273
  },
  {
    "iter": 11,
    "ep_wins": 8,
    "ep_losses": 24,
    "ep_draws": 0,
    "recent_winrate": 0.25,
    "policy_loss": -0.004136554018746759,
    "value_loss": 0.28384126154237843,
    "entropy": 0.4139489752178023,
    "elapsed_s": 148.6127797579975
  },
  {
    "iter": 12,
    "ep_wins": 11,
    "ep_losses": 21,
    "ep_draws": 0,
    "recent_winrate": 0.34375,
    "policy_loss": -0.00435333145113596,
    "value_loss": 0.2955375615454028,
    "entropy": 0.3915905072359198,
    "elapsed_s": 160.34065198199823
  },
  {
    "iter": 13,
    "ep_wins": 10,
    "ep_losses": 22,
    "ep_draws": 0,
    "recent_winrate": 0.3125,
    "policy_loss": 0.002374332633795954,
    "value_loss": 0.26606690084278795,
    "entropy": 0.3946531184347248,
    "elapsed_s": 171.63248513397411
  },
  {
    "iter": 14,
    "ep_wins": 5,
    "ep_losses": 27,
    "ep_draws": 0,
    "recent_winrate": 0.15625,
    "policy_loss": -0.007588759403512085,
    "value_loss": 0.1962467667863454,
    "entropy": 0.43605258093008414,
    "elapsed_s": 186.54938704997767
  },
  {
    "iter": 15,
    "ep_wins": 6,
    "ep_losses": 26,
    "ep_draws": 0,
    "recent_winrate": 0.1875,
    "policy_loss": -0.009642883915368158,
    "value_loss": 0.20157590686394605,
    "entropy": 0.4010984216498481,
    "elapsed_s": 199.63353132398333
  },
  {
    "iter": 16,
    "ep_wins": 3,
    "ep_losses": 29,
    "ep_draws": 0,
    "recent_winrate": 0.09375,
    "policy_loss": -0.007555190503778022,
    "value_loss": 0.1949740048889045,
    "entropy": 0.389250440495129,
    "elapsed_s": 212.3099093689816
  },
  {
    "iter": 17,
    "ep_wins": 15,
    "ep_losses": 17,
    "ep_draws": 0,
    "recent_winrate": 0.46875,
    "policy_loss": 0.0014543448718541186,
    "value_loss": 0.34828137017495897,
    "entropy": 0.39584087974982085,
    "elapsed_s": 226.33783873499488
  },
  {
    "iter": 18,
    "ep_wins": 6,
    "ep_losses": 26,
    "ep_draws": 0,
    "recent_winrate": 0.1875,
    "policy_loss": -0.006649743927491079,
    "value_loss": 0.23295352867799393,
    "entropy": 0.41111978432739166,
    "elapsed_s": 239.82361621098244
  },
  {
    "iter": 19,
    "ep_wins": 8,
    "ep_losses": 24,
    "ep_draws": 0,
    "recent_winrate": 0.25,
    "policy_loss": -0.005831025633142417,
    "value_loss": 0.30254510056770434,
    "entropy": 0.4304299846922688,
    "elapsed_s": 252.42416661197785
  },
  {
    "iter": 20,
    "ep_wins": 7,
    "ep_losses": 25,
    "ep_draws": 0,
    "recent_winrate": 0.21875,
    "policy_loss": -0.003960380888404163,
    "value_loss": 0.22310567431777498,
    "entropy": 0.39131001153013445,
    "elapsed_s": 266.53484459398896
  },
  {
    "iter": 21,
    "ep_wins": 7,
    "ep_losses": 25,
    "ep_draws": 0,
    "recent_winrate": 0.21875,
    "policy_loss": -0.004107242408714258,
    "value_loss": 0.23316450924398024,
    "entropy": 0.38131659969736814,
    "elapsed_s": 279.5633563329757
  },
  {
    "iter": 22,
    "ep_wins": 6,
    "ep_losses": 26,
    "ep_draws": 0,
    "recent_winrate": 0.1875,
    "policy_loss": -0.007568507705377084,
    "value_loss": 0.24923186763697577,
    "entropy": 0.40086483580176885,
    "elapsed_s": 291.9517430109845
  },
  {
    "iter": 23,
    "ep_wins": 9,
    "ep_losses": 23,
    "ep_draws": 0,
    "recent_winrate": 0.28125,
    "policy_loss": -0.004508910243506154,
    "value_loss": 0.3095732040893475,
    "entropy": 0.403324688381395,
    "elapsed_s": 305.9688935659942
  },
  {
    "iter": 24,
    "ep_wins": 6,
    "ep_losses": 26,
    "ep_draws": 0,
    "recent_winrate": 0.1875,
    "policy_loss": -0.010010459380282555,
    "value_loss": 0.21816852655682673,
    "entropy": 0.4156058068561337,
    "elapsed_s": 317.75579610298155
  },
  {
    "iter": 25,
    "ep_wins": 5,
    "ep_losses": 27,
    "ep_draws": 0,
    "recent_winrate": 0.15625,
    "policy_loss": -0.023296347763511624,
    "value_loss": 0.24363910487950965,
    "entropy": 0.4157186556398906,
    "elapsed_s": 330.06012997799553
  },
  {
    "iter": 26,
    "ep_wins": 7,
    "ep_losses": 25,
    "ep_draws": 0,
    "recent_winrate": 0.21875,
    "policy_loss": -0.007052759683192786,
    "value_loss": 0.177321002174241,
    "entropy": 0.3900002060314065,
    "elapsed_s": 343.16179433997604
  },
  {
    "iter": 27,
    "ep_wins": 8,
    "ep_losses": 24,
    "ep_draws": 0,
    "recent_winrate": 0.25,
    "policy_loss": -0.0035626606493774117,
    "value_loss": 0.2687461170872949,
    "entropy": 0.3704103596235932,
    "elapsed_s": 355.7421701819985
  },
  {
    "iter": 28,
    "ep_wins": 11,
    "ep_losses": 21,
    "ep_draws": 0,
    "recent_winrate": 0.34375,
    "policy_loss": -0.006862794753491908,
    "value_loss": 0.3065414310459597,
    "entropy": 0.38886166122931387,
    "elapsed_s": 368.00766804697923
  },
  {
    "iter": 29,
    "ep_wins": 8,
    "ep_losses": 24,
    "ep_draws": 0,
    "recent_winrate": 0.25,
    "policy_loss": 5.1921841236075916e-05,
    "value_loss": 0.278729407375001,
    "entropy": 0.408179722656475,
    "elapsed_s": 382.83532711298903
  },
  {
    "iter": 30,
    "ep_wins": 4,
    "ep_losses": 28,
    "ep_draws": 0,
    "recent_winrate": 0.125,
    "policy_loss": -0.009047089066170796,
    "value_loss": 0.19327854963534186,
    "entropy": 0.3910507744529853,
    "elapsed_s": 396.4750734719855
  },
  {
    "iter": 31,
    "ep_wins": 13,
    "ep_losses": 19,
    "ep_draws": 0,
    "recent_winrate": 0.40625,
    "policy_loss": -0.007325175741326264,
    "value_loss": 0.3111073844265316,
    "entropy": 0.3997754925572148,
    "elapsed_s": 412.42528279399266
  },
  {
    "iter": 32,
    "ep_wins": 11,
    "ep_losses": 21,
    "ep_draws": 0,
    "recent_winrate": 0.34375,
    "policy_loss": -0.011194014581759892,
    "value_loss": 0.2840604168039596,
    "entropy": 0.4048791312487867,
    "elapsed_s": 425.9985695039795
  },
  {
    "iter": 33,
    "ep_wins": 8,
    "ep_losses": 24,
    "ep_draws": 0,
    "recent_winrate": 0.25,
    "policy_loss": -0.00505625005501977,
    "value_loss": 0.24650249156157944,
    "entropy": 0.4480807012899704,
    "elapsed_s": 439.32596866597305
  },
  {
    "iter": 34,
    "ep_wins": 5,
    "ep_losses": 27,
    "ep_draws": 0,
    "recent_winrate": 0.15625,
    "policy_loss": -0.001345131992387732,
    "value_loss": 0.20470676680950378,
    "entropy": 0.42187988416932354,
    "elapsed_s": 452.0200257349934
  },
  {
    "iter": 35,
    "ep_wins": 6,
    "ep_losses": 26,
    "ep_draws": 0,
    "recent_winrate": 0.1875,
    "policy_loss": -0.0074444317060119326,
    "value_loss": 0.1761295985112474,
    "entropy": 0.3918091838740371,
    "elapsed_s": 464.5970417899953
  },
  {
    "iter": 36,
    "ep_wins": 4,
    "ep_losses": 28,
    "ep_draws": 0,
    "recent_winrate": 0.125,
    "policy_loss": -0.005299021155484037,
    "value_loss": 0.19831823987785538,
    "entropy": 0.36504748210601873,
    "elapsed_s": 480.3918538199796
  },
  {
    "iter": 37,
    "ep_wins": 4,
    "ep_losses": 28,
    "ep_draws": 0,
    "recent_winrate": 0.125,
    "policy_loss": 0.004363438855943968,
    "value_loss": 0.16312745917337806,
    "entropy": 0.42403084673227187,
    "elapsed_s": 494.5482911229774
  },
  {
    "iter": 38,
    "ep_wins": 4,
    "ep_losses": 28,
    "ep_draws": 0,
    "recent_winrate": 0.125,
    "policy_loss": -0.006316755034583637,
    "value_loss": 0.12499323262808043,
    "entropy": 0.38374073352842103,
    "elapsed_s": 507.58639930098434
  },
  {
    "iter": 39,
    "ep_wins": 10,
    "ep_losses": 22,
    "ep_draws": 0,
    "recent_winrate": 0.3125,
    "policy_loss": 0.019361100892183458,
    "value_loss": 0.28398010029319853,
    "entropy": 0.36996598425649757,
    "elapsed_s": 519.2953946439957
  },
  {
    "iter": 40,
    "ep_wins": 4,
    "ep_losses": 28,
    "ep_draws": 0,
    "recent_winrate": 0.125,
    "policy_loss": -0.009104430629942959,
    "value_loss": 0.175612757154277,
    "entropy": 0.3787022013597805,
    "elapsed_s": 533.8248000689782
  }
]
