[
  {
    "iter": 1,
    "ep_wins": 10,
    "ep_losses": 22,
    "ep_draws": 0,
    "recent_winrate": 0.3125,
    "policy_loss": -0.0009207933008692942,
    "value_loss": 0.3940252014707524,
    "entropy": 0.6604018079702686,
    "elapsed_s": 12.131483764998848
  },
  {
    "iter": 2,
    "ep_wins": 8,
    "ep_losses": 24,
    "ep_draws": 0,
    "recent_winrate": 0.25,
    "policy_loss": 0.002146006579516315,
    "value_loss": 0.34407244502763684,
    "entropy": 0.6654572716320466,
    "elapsed_s": 25.607867356971838
  },
  {
    "iter": 3,
    "ep_wins": 7,
    "ep_losses": 25,
    "ep_draws": 0,
    "recent_winrate": 0.21875,
    "policy_loss": -0.044128100621765046,
    "value_loss": 0.2653874146573836,
    "entropy": 0.5777754079459164,
    "elapsed_s": 40.31699548798497
  },
  {
    "iter": 4,
    "ep_wins": 9,
    "ep_losses": 23,
    "ep_draws": 0,
    "recent_winrate": 0.28125,
    "policy_loss": -0.0064947078811125394,
    "value_loss": 0.3064307682565074,
    "entropy": 0.597780170153378,
    "elapsed_s": 52.84669446799671
  },
  {
    "iter": 5,
    "ep_wins": 5,
    "ep_losses": 27,
    "ep_draws": 0,
    "recent_winrate": 0.15625,
    "policy_loss": 0.0004986964697095318,
    "value_loss": 0.23349575282421045,
    "entropy": 0.5771088189171899,
    "elapsed_s": 66.61899274599273
  },
  {
    "iter": 6,
    "ep_wins": 6,
    "ep_losses": 25,
    "ep_draws": 1,
    "recent_winrate": 0.1875,
    "policy_loss": -0.0013188063107312104,
    "value_loss": 0.273275227320141,
    "entropy": 0.6089192306678421,
    "elapsed_s": 81.14798112798599
  },
  {
    "iter": 7,
    "ep_wins": 7,
    "ep_losses": 25,
    "ep_draws": 0,
    "recent_winrate": 0.21875,
    "policy_loss": -0.0013313649575239753,
    "value_loss": 0.29372888231714495,
    "entropy": 0.5706589616580904,
    "elapsed_s": 94.51768423599424
  },
  {
    "iter": 8,
    "ep_wins": 7,
    "ep_losses": 25,
    "ep_draws": 0,
    "recent_winrate": 0.21875,
    "policy_loss": -0.0012306738226297554,
    "value_loss": 0.3635551547408569,
    "entropy": 0.6141311449903581,
    "elapsed_s": 105.46113623899873
  },
  {
    "iter": 9,
    "ep_wins": 4,
    "ep_losses": 28,
    "ep_draws": 0,
    "recent_winrate": 0.125,
    "policy_loss": 0.000692524670753869,
    "value_loss": 0.18798610258707144,
    "entropy": 0.5649131491494519,
    "elapsed_s": 118.01828198399744
  },
  {
    "iter": 10,
    "ep_wins": 7,
    "ep_losses": 25,
    "ep_draws": 0,
    "recent_winrate": 0.21875,
    "policy_loss": -0.0031374434486032055,
    "value_loss": 0.366717837785705,
    "entropy": 0.6644460357235936,
    "elapsed_s": 131.23967158899177
  },
  {
    "iter": 11,
    "ep_wins": 4,
    "ep_losses": 28,
    "ep_draws": 0,
    "recent_winrate": 0.125,
    "policy_loss": -0.0003196126143323381,
    "value_loss": 0.18975970479628082,
    "entropy": 0.628560434397906,
    "elapsed_s": 144.45669119397644
  },
  {
    "iter": 12,
    "ep_wins": 6,
    "ep_losses": 26,
    "ep_draws": 0,
    "recent_winrate": 0.1875,
    "policy_loss": -0.01827889507348161,
    "value_loss": 0.2706191278496114,
    "entropy": 0.5966458580669154,
    "elapsed_s": 159.52586118597537
  },
  {
    "iter": 13,
    "ep_wins": 12,
    "ep_losses": 20,
    "ep_draws": 0,
    "recent_winrate": 0.375,
    "policy_loss": -4.82905825265334e-05,
    "value_loss": 0.4046492785490067,
    "entropy": 0.6133669603559445,
    "elapsed_s": 171.96174085099483
  },
  {
    "iter": 14,
    "ep_wins": 9,
    "ep_losses": 23,
    "ep_draws": 0,
    "recent_winrate": 0.28125,
    "policy_loss": 0.002748730051353049,
    "value_loss": 0.28287932872919114,
    "entropy": 0.6240335231353985,
    "elapsed_s": 186.2475109959778
  },
  {
    "iter": 15,
    "ep_wins": 9,
    "ep_losses": 23,
    "ep_draws": 0,
    "recent_winrate": 0.28125,
    "policy_loss": -0.00023236454614152123,
    "value_loss": 0.38968430871477316,
    "entropy": 0.5987340694689274,
    "elapsed_s": 199.69617692098836
  },
  {
    "iter": 16,
    "ep_wins": 7,
    "ep_losses": 25,
    "ep_draws": 0,
    "recent_winrate": 0.21875,
    "policy_loss": -0.0008006588696074541,
    "value_loss": 0.28799919358175763,
    "entropy": 0.5776619183858216,
    "elapsed_s": 211.94086600997252
  },
  {
    "iter": 17,
    "ep_wins": 5,
    "ep_losses": 27,
    "ep_draws": 0,
    "recent_winrate": 0.15625,
    "policy_loss": -0.005366476521380216,
    "value_loss": 0.25425350772249733,
    "entropy": 0.6184558791024518,
    "elapsed_s": 224.9382508949784
  },
  {
    "iter": 18,
    "ep_wins": 8,
    "ep_losses": 24,
    "ep_draws": 0,
    "recent_winrate": 0.25,
    "policy_loss": 1.799436618238582e-05,
    "value_loss": 0.23448669101275843,
    "entropy": 0.6003827660089436,
    "elapsed_s": 238.54897798999446
  },
  {
    "iter": 19,
    "ep_wins": 8,
    "ep_losses": 24,
    "ep_draws": 0,
    "recent_winrate": 0.25,
    "policy_loss": -0.001274505370395578,
    "value_loss": 0.33780019088401964,
    "entropy": 0.6036482911139046,
    "elapsed_s": 252.40823565598112
  },
  {
    "iter": 20,
    "ep_wins": 9,
    "ep_losses": 23,
    "ep_draws": 0,
    "recent_winrate": 0.28125,
    "policy_loss": -0.004201731360581107,
    "value_loss": 0.29362961984130775,
    "entropy": 0.6817741307529767,
    "elapsed_s": 264.05557620699983
  },
  {
    "iter": 21,
    "ep_wins": 7,
    "ep_losses": 25,
    "ep_draws": 0,
    "recent_winrate": 0.21875,
    "policy_loss": 0.025285176386912807,
    "value_loss": 0.28275569133378936,
    "entropy": 0.6095052611890652,
    "elapsed_s": 277.0238869229797
  },
  {
    "iter": 22,
    "ep_wins": 9,
    "ep_losses": 23,
    "ep_draws": 0,
    "recent_winrate": 0.28125,
    "policy_loss": 0.0001574679819680975,
    "value_loss": 0.27515038390518554,
    "entropy": 0.6311606975350295,
    "elapsed_s": 288.57907399497344
  },
  {
    "iter": 23,
    "ep_wins": 6,
    "ep_losses": 26,
    "ep_draws": 0,
    "recent_winrate": 0.1875,
    "policy_loss": 0.00024863293940434076,
    "value_loss": 0.2579772043061613,
    "entropy": 0.6052191548988991,
    "elapsed_s": 302.086378795997
  },
  {
    "iter": 24,
    "ep_wins": 7,
    "ep_losses": 25,
    "ep_draws": 0,
    "recent_winrate": 0.21875,
    "policy_loss": -0.00042489876351046855,
    "value_loss": 0.2910593763086463,
    "entropy": 0.609214765407311,
    "elapsed_s": 316.0694077129883
  },
  {
    "iter": 25,
    "ep_wins": 7,
    "ep_losses": 25,
    "ep_draws": 0,
    "recent_winrate": 0.21875,
    "policy_loss": 5.004904182797958e-05,
    "value_loss": 0.3150908001235574,
    "entropy": 0.6235723642192966,
    "elapsed_s": 329.6296822859731
  },
  {
    "iter": 26,
    "ep_wins": 7,
    "ep_losses": 25,
    "ep_draws": 0,
    "recent_winrate": 0.21875,
    "policy_loss": -0.0009293598133518276,
    "value_loss": 0.23594113958368676,
    "entropy": 0.6025708385738862,
    "elapsed_s": 342.5547199979774
  },
  {
    "iter": 27,
    "ep_wins": 8,
    "ep_losses": 24,
    "ep_draws": 0,
    "recent_winrate": 0.25,
    "policy_loss": -3.6821544906868236e-05,
    "value_loss": 0.3011348766151573,
    "entropy": 0.6071497430772044,
    "elapsed_s": 356.70692643299117
  },
  {
    "iter": 28,
    "ep_wins": 8,
    "ep_losses": 24,
    "ep_draws": 0,
    "recent_winrate": 0.25,
    "policy_loss": 9.227548391209095e-05,
    "value_loss": 0.31730766551221423,
    "entropy": 0.555585405463174,
    "elapsed_s": 371.50208375498187
  },
  {
    "iter": 29,
    "ep_wins": 10,
    "ep_losses": 22,
    "ep_draws": 0,
    "recent_winrate": 0.3125,
    "policy_loss": 0.0019668439150136137,
    "value_loss": 0.28116037989313725,
    "entropy": 0.6295323417381496,
    "elapsed_s": 385.8999409059761
  },
  {
    "iter": 30,
    "ep_wins": 7,
    "ep_losses": 25,
    "ep_draws": 0,
    "recent_winrate": 0.21875,
    "policy_loss": 0.00030825276570937743,
    "value_loss": 0.2771850405432126,
    "entropy": 0.5964869507214847,
    "elapsed_s": 399.1997968709911
  },
  {
    "iter": 31,
    "ep_wins": 9,
    "ep_losses": 23,
    "ep_draws": 0,
    "recent_winrate": 0.28125,
    "policy_loss": -0.00028464626277895956,
    "value_loss": 0.3263570170252064,
    "entropy": 0.6524217707482085,
    "elapsed_s": 411.65560807299335
  },
  {
    "iter": 32,
    "ep_wins": 10,
    "ep_losses": 22,
    "ep_draws": 0,
    "recent_winrate": 0.3125,
    "policy_loss": -0.00035709975097887977,
    "value_loss": 0.3405288791636809,
    "entropy": 0.5769363464331451,
    "elapsed_s": 425.6014944019844
  },
  {
    "iter": 33,
    "ep_wins": 7,
    "ep_losses": 25,
    "ep_draws": 0,
    "recent_winrate": 0.21875,
    "policy_loss": 0.003442854936418585,
    "value_loss": 0.23637678367110262,
    "entropy": 0.6090587454298102,
    "elapsed_s": 437.39033046897384
  },
  {
    "iter": 34,
    "ep_wins": 4,
    "ep_losses": 28,
    "ep_draws": 0,
    "recent_winrate": 0.125,
    "policy_loss": -0.001035946288039649,
    "value_loss": 0.19051258241143007,
    "entropy": 0.5552675295104611,
    "elapsed_s": 450.277836674999
  },
  {
    "iter": 35,
    "ep_wins": 4,
    "ep_losses": 28,
    "ep_draws": 0,
    "recent_winrate": 0.125,
    "policy_loss": 1.6545908827674137e-05,
    "value_loss": 0.22615757425639316,
    "entropy": 0.6484950717520859,
    "elapsed_s": 462.69325935898814
  },
  {
    "iter": 36,
    "ep_wins": 4,
    "ep_losses": 28,
    "ep_draws": 0,
    "recent_winrate": 0.125,
    "policy_loss": 0.023063651508030154,
    "value_loss": 0.22504713724206446,
    "entropy": 0.6642519582990554,
    "elapsed_s": 476.25231853398145
  },
  {
    "iter": 37,
    "ep_wins": 7,
    "ep_losses": 25,
    "ep_draws": 0,
    "recent_winrate": 0.21875,
    "policy_loss": 0.0029152020457399045,
    "value_loss": 0.2990576028937779,
    "entropy": 0.6101725231142416,
    "elapsed_s": 487.8403872309718
  },
  {
    "iter": 38,
    "ep_wins": 8,
    "ep_losses": 24,
    "ep_draws": 0,
    "recent_winrate": 0.25,
    "policy_loss": 0.0002856536608154146,
    "value_loss": 0.24125374018070567,
    "entropy": 0.6814337048329908,
    "elapsed_s": 500.45414784597233
  },
  {
    "iter": 39,
    "ep_wins": 5,
    "ep_losses": 27,
    "ep_draws": 0,
    "recent_winrate": 0.15625,
    "policy_loss": 0.00038435942414729446,
    "value_loss": 0.30149773345307396,
    "entropy": 0.6026316697493294,
    "elapsed_s": 513.9980309609964
  },
  {
    "iter": 40,
    "ep_wins": 6,
    "ep_losses": 26,
    "ep_draws": 0,
    "recent_winrate": 0.1875,
    "policy_loss": -0.007396103059373775,
    "value_loss": 0.2816196937163953,
    "entropy": 0.5803467297063816,
    "elapsed_s": 526.6045697239751
  }
]
